piviz/__init__.py
piviz/core/__init__.py
piviz/core/camera.py
piviz/core/exporter.py
piviz/core/scene.py
piviz/core/studio.py
piviz/core/theme.py
piviz/core/usd_player.py
piviz/graphics/__init__.py
piviz/graphics/colors.py
piviz/graphics/environment.py
piviz/graphics/primitives.py
piviz/ui/__init__.py
piviz/ui/manager.py
piviz/ui/overlay.py
piviz/ui/viewcube.py
piviz/ui/widgets.py
piviz_3d-0.1.1.dist-info/licenses/LICENSE
piviz_3d-0.1.1.dist-info/METADATA
piviz_3d-0.1.1.dist-info/WHEEL
piviz_3d-0.1.1.dist-info/entry_points.txt
piviz_3d-0.1.1.dist-info/top_level.txt
piviz_3d-0.1.1.dist-info/RECORD
