Metadata-Version: 2.4
Name: piviz-3d
Version: 0.1.1
Summary: Modern GPU-accelerated 3D visualization framework for scientific computing
Author-email: Yogesh Phalak <yogeshphalak31415@gmail.com>
License: Apache-2.0
Project-URL: Homepage, https://github.com/PhalcoAi/PiViz
Project-URL: Documentation, https://github.com/PhalcoAi/PiViz#readme
Project-URL: Repository, https://github.com/PhalcoAi/PiViz
Project-URL: Issues, https://github.com/PhalcoAi/PiViz/issues
Keywords: visualization,3d,graphics,opengl,moderngl,scientific,simulation,gpu,usd,physics
Classifier: Development Status :: 4 - Beta
Classifier: Intended Audience :: Developers
Classifier: Intended Audience :: Science/Research
Classifier: License :: OSI Approved :: Apache Software License
Classifier: Operating System :: OS Independent
Classifier: Programming Language :: Python :: 3
Classifier: Programming Language :: Python :: 3.8
Classifier: Programming Language :: Python :: 3.9
Classifier: Programming Language :: Python :: 3.10
Classifier: Programming Language :: Python :: 3.11
Classifier: Programming Language :: Python :: 3.12
Classifier: Topic :: Scientific/Engineering :: Visualization
Classifier: Topic :: Multimedia :: Graphics :: 3D Rendering
Requires-Python: >=3.8
License-File: LICENSE
Requires-Dist: moderngl>=5.8.0
Requires-Dist: moderngl-window>=2.4.0
Requires-Dist: imgui>=2.0.0
Requires-Dist: numpy>=1.20.0
Requires-Dist: psutil>=5.8.0
Requires-Dist: imageio[ffmpeg]>=2.30.0
Requires-Dist: usd-core>=23.08; platform_machine != "aarch64"
Requires-Dist: GPUtil>=1.4.0
Provides-Extra: dev
Requires-Dist: pytest>=7.0.0; extra == "dev"
Requires-Dist: black>=23.0.0; extra == "dev"
Requires-Dist: isort>=5.12.0; extra == "dev"
Requires-Dist: mypy>=1.0.0; extra == "dev"
Provides-Extra: all
Requires-Dist: piviz[dev]; extra == "all"
Dynamic: license-file
